plably/__init__.py
plably/__main__.py
plably/plot.py
plably/props.py
plably-0.1.8.dist-info/LICENSE
plably-0.1.8.dist-info/METADATA
plably-0.1.8.dist-info/WHEEL
plably-0.1.8.dist-info/entry_points.txt
plably-0.1.8.dist-info/top_level.txt
plably-0.1.8.dist-info/RECORD
