Metadata-Version: 2.1
Name: plably
Version: 0.1.8
Summary: A simple plotly utility to generate graphs for my lab reports.
Home-page: https://github.com/DhruvBisla/plably
Author: Dhruv Bisla
Author-email: bisladhruv@gmail.com
License: MIT
Keywords: plotly,graphs,utility,lab-report
Platform: UNKNOWN
Classifier: Intended Audience :: Developers
Classifier: Programming Language :: Python :: 3
Classifier: License :: OSI Approved :: MIT License
Classifier: Operating System :: OS Independent
Requires: numpy
Requires: pandas
Requires: plotly
Requires: kaleido
Requires-Python: >=3.6
Requires-Dist: numpy
Requires-Dist: pandas
Requires-Dist: plotly
Requires-Dist: kaleido
